pydropsonde/__init__.py
pydropsonde/circles.py
pydropsonde/main.py
pydropsonde/pipeline.py
pydropsonde/processor.py
pydropsonde/helper/__init__.py
pydropsonde/helper/paths.py
pydropsonde/helper/physics.py
pydropsonde/helper/quality.py
pydropsonde/helper/rawreader.py
pydropsonde/helper/stats.py
pydropsonde/helper/xarray_helper.py
pydropsonde-0.5.1.dist-info/METADATA
pydropsonde-0.5.1.dist-info/WHEEL
pydropsonde-0.5.1.dist-info/entry_points.txt
pydropsonde-0.5.1.dist-info/licenses/LICENSE
pydropsonde-0.5.1.dist-info/RECORD
